djangoformsetjs/__init__.py
djangoformsetjs/utils.py
djangoformsetjs/static/js/jquery.formset.js
djangoformsetjs/static/js/jquery.formset.min.js
djangoformsetjs/templatetags/__init__.py
djangoformsetjs/templatetags/formset_tags.py
django_formset_js_improved-0.5.0.4.dist-info/AUTHORS
django_formset_js_improved-0.5.0.4.dist-info/LICENSE
django_formset_js_improved-0.5.0.4.dist-info/METADATA
django_formset_js_improved-0.5.0.4.dist-info/WHEEL
django_formset_js_improved-0.5.0.4.dist-info/top_level.txt
django_formset_js_improved-0.5.0.4.dist-info/RECORD
