Metadata-Version: 2.2
Name: django-formset-js-improved
Version: 0.5.0.4
Summary: Extend Django formsets with JavaScript
Home-page: https://github.com/pretix/django-formset-js
Author: Raphael Michel
Author-email: mail@raphaelmichel.de
License: BSD
Classifier: Environment :: Web Environment
Classifier: Intended Audience :: Developers
Classifier: Operating System :: OS Independent
Classifier: Programming Language :: Python
Classifier: Framework :: Django
Classifier: License :: OSI Approved :: BSD License
License-File: LICENSE
License-File: AUTHORS
Requires-Dist: Django
Requires-Dist: django-jquery-js
Dynamic: author
Dynamic: author-email
Dynamic: classifier
Dynamic: description
Dynamic: home-page
Dynamic: license
Dynamic: requires-dist
Dynamic: summary
